{"displayFieldName":"market_name","fieldAliases":{"OBJECTID":"OBJECTID","market_name":"市招名稱","addr":"販售場所地址","business_week":"營業時間星期","context":"店家介紹","ValidDate":"標章有效期限","Lontitude":"經度","Latitude":"緯度","case_code":"案件編號","created_user":"created_user","created_date":"created_date","last_edited_user":"last_edited_user","last_edited_date":"last_edited_date","type":"營業類別","badge_code":"標章編號","business_hours":"營業開始時間","business_hours_end":"營業結束時間","AddrToLonLatProcTime":"地址轉換坐標處理時間","AddrToLonLatProcLog":"地址轉換坐標處理紀錄","URL1":"URL1","URL2":"URL2","URL3":"URL3"},"geometryType":"esriGeometryPoint","spatialReference":{"wkid":4326,"latestWkid":4326},"fields":[{"name":"OBJECTID","type":"esriFieldTypeOID","alias":"OBJECTID"},{"name":"market_name","type":"esriFieldTypeString","alias":"市招名稱","length":100},{"name":"addr","type":"esriFieldTypeString","alias":"販售場所地址","length":50},{"name":"business_week","type":"esriFieldTypeString","alias":"營業時間星期","length":100},{"name":"context","type":"esriFieldTypeString","alias":"店家介紹","length":300},{"name":"ValidDate","type":"esriFieldTypeDate","alias":"標章有效期限","length":8},{"name":"Lontitude","type":"esriFieldTypeDouble","alias":"經度"},{"name":"Latitude","type":"esriFieldTypeDouble","alias":"緯度"},{"name":"case_code","type":"esriFieldTypeString","alias":"案件編號","length":20},{"name":"created_user","type":"esriFieldTypeString","alias":"created_user","length":255},{"name":"created_date","type":"esriFieldTypeDate","alias":"created_date","length":8},{"name":"last_edited_user","type":"esriFieldTypeString","alias":"last_edited_user","length":255},{"name":"last_edited_date","type":"esriFieldTypeDate","alias":"last_edited_date","length":8},{"name":"type","type":"esriFieldTypeString","alias":"營業類別","length":20},{"name":"badge_code","type":"esriFieldTypeString","alias":"標章編號","length":20},{"name":"business_hours","type":"esriFieldTypeString","alias":"營業開始時間","length":50},{"name":"business_hours_end","type":"esriFieldTypeString","alias":"營業結束時間","length":50},{"name":"AddrToLonLatProcTime","type":"esriFieldTypeDate","alias":"地址轉換坐標處理時間","length":8},{"name":"AddrToLonLatProcLog","type":"esriFieldTypeString","alias":"地址轉換坐標處理紀錄","length":255},{"name":"URL1","type":"esriFieldTypeString","alias":"URL1","length":65},{"name":"URL2","type":"esriFieldTypeString","alias":"URL2","length":65},{"name":"URL3","type":"esriFieldTypeString","alias":"URL3","length":65}],"features":[{"attributes":{"OBJECTID":73437,"market_name":"蘇 飯糰蘿蔔絲","addr":"新北市汐止區林森街北二高架橋下","business_week":"星期二,星期三,星期四,星期五,星期六,星期日","context":"各式早餐簡便食品","ValidDate":1713801600000,"Lontitude":121.6244012,"Latitude":25.0406615,"case_code":"2021041200038","created_user":"godspeed","created_date":1619671025000,"last_edited_user":"Developer","last_edited_date":1619996004000,"type":"販售","badge_code":"D005057","business_hours":"05:00","business_hours_end":"00:00","AddrToLonLatProcTime":1620023923000,"AddrToLonLatProcLog":"處理成功:Google","URL1":"https://taiwanpork.coa.gov.tw/files/food_data/14842/A01.jpg","URL2":"","URL3":""},"geometry":{"x":121.62440120000008,"y":25.040661500000056}},{"attributes":{"OBJECTID":73438,"market_name":"水碓紅麵線","addr":"新北市淡水區重建街225號","business_week":"星期一,星期二,星期三,星期四,星期五,星期六,星期日","context":"特製大腸紅麵線","ValidDate":1713801600000,"Lontitude":121.4414,"Latitude":25.175111,"case_code":"2021041200056","created_user":"godspeed","created_date":1619671027000,"last_edited_user":"Developer","last_edited_date":1619996004000,"type":"餐飲","badge_code":"D005059","business_hours":"05:30","business_hours_end":"11:00","AddrToLonLatProcTime":1620023923000,"AddrToLonLatProcLog":"處理成功:TGOS","URL1":"https://taiwanpork.coa.gov.tw/files/food_data/14860/A01.jpg","URL2":"","URL3":""},"geometry":{"x":121.44140000000004,"y":25.175111000000072}},{"attributes":{"OBJECTID":73439,"market_name":"老媽生鮮蔬果行","addr":"新北市汐止區林森街北二高架橋下","business_week":"星期二,星期三,星期四,星期五,星期六,星期日","context":"","ValidDate":1713801600000,"Lontitude":121.6244012,"Latitude":25.0406615,"case_code":"2021041200043","created_user":"godspeed","created_date":1619671028000,"last_edited_user":"Developer","last_edited_date":1619996004000,"type":"販售","badge_code":"D005058","business_hours":"07:00","business_hours_end":"12:00","AddrToLonLatProcTime":1620023923000,"AddrToLonLatProcLog":"處理成功:Google","URL1":"https://taiwanpork.coa.gov.tw/files/food_data/14847/A01.jpg","URL2":"","URL3":""},"geometry":{"x":121.62440120000008,"y":25.040661500000056}},{"attributes":{"OBJECTID":73440,"market_name":"王媽媽自助餐","addr":"新北市汐止區復興路52號","business_week":"星期一,星期二,星期三,星期四,星期五","context":"炸排骨焢肉飯","ValidDate":1713801600000,"Lontitude":121.6568,"Latitude":25.062626,"case_code":"2021041200078","created_user":"godspeed","created_date":1619671054000,"last_edited_user":"Developer","last_edited_date":1619996004000,"type":"餐飲","badge_code":"D005060","business_hours":"10:45","business_hours_end":"14:00","AddrToLonLatProcTime":1620023923000,"AddrToLonLatProcLog":"處理成功:TGOS","URL1":"https://taiwanpork.coa.gov.tw/files/food_data/14882/A01.jpg","URL2":"","URL3":""},"geometry":{"x":121.65680000000009,"y":25.062626000000023}},{"attributes":{"OBJECTID":73441,"market_name":"新美味熱炒","addr":"新北市汐止區水源路一段265號","business_week":"星期二,星期三,星期四,星期五,星期六,星期日","context":"炒飯 炒麵  炒菜","ValidDate":1713801600000,"Lontitude":121.65415,"Latitude":25.059383,"case_code":"2021041200079","created_user":"godspeed","created_date":1619671056000,"last_edited_user":"Developer","last_edited_date":1619996004000,"type":"餐飲","badge_code":"D005061","business_hours":"11:00","business_hours_end":"21:00","AddrToLonLatProcTime":1620023923000,"AddrToLonLatProcLog":"處理成功:TGOS","URL1":"https://taiwanpork.coa.gov.tw/files/food_data/14883/A01.jpg","URL2":"","URL3":""},"geometry":{"x":121.65415000000007,"y":25.059383000000025}},{"attributes":{"OBJECTID":73442,"market_name":"吉利行","addr":"新竹縣竹北市竹仁街46之6號","business_week":"星期一,星期二,星期三,星期四,星期五,星期六,星期日","context":"販賣快炒熟食","ValidDate":1713801600000,"Lontitude":121.010581,"Latitude":24.837336,"case_code":"2021040100024","created_user":"godspeed","created_date":1619671060000,"last_edited_user":"Developer","last_edited_date":1619996004000,"type":"販售","badge_code":"D005062","business_hours":"05:00","business_hours_end":"13:00","AddrToLonLatProcTime":1620023923000,"AddrToLonLatProcLog":"處理成功:TGOS","URL1":"https://taiwanpork.coa.gov.tw/files/food_data/14427/A01.jpg","URL2":"","URL3":""},"geometry":{"x":121.01058100000012,"y":24.83733600000005}},{"attributes":{"OBJECTID":73443,"market_name":"吉品客家菜","addr":"新竹縣竹北市仁愛街45號內 (竹北第一市場攤販56號)","business_week":"星期二,星期三,星期四,星期五,星期六,星期日","context":"吉品客家菜，本店售焢肉、客家小炒，均使用國產豬肉","ValidDate":1713801600000,"Lontitude":121.010769,"Latitude":24.837299,"case_code":"2021040600033","created_user":"godspeed","created_date":1619671062000,"last_edited_user":"Developer","last_edited_date":1619996004000,"type":"餐飲","badge_code":"D005063","business_hours":"05:00","business_hours_end":"13:00","AddrToLonLatProcTime":1620023923000,"AddrToLonLatProcLog":"處理成功:TGOS","URL1":"https://taiwanpork.coa.gov.tw/files/food_data/14526/A01.jpg","URL2":"","URL3":""},"geometry":{"x":121.0107690000001,"y":24.83729900000003}},{"attributes":{"OBJECTID":73444,"market_name":"京華牛肉麵","addr":"新竹縣新埔鎮仁愛路5號　","business_week":"星期一,星期五,星期六,星期日","context":"眷村媽媽好味道","ValidDate":1713801600000,"Lontitude":121.080959,"Latitude":24.827235,"case_code":"2021040600039","created_user":"godspeed","created_date":1619671064000,"last_edited_user":"Developer","last_edited_date":1619996004000,"type":"工廠與製造","badge_code":"D005064","business_hours":"11:30","business_hours_end":"21:00","AddrToLonLatProcTime":1620023923000,"AddrToLonLatProcLog":"處理成功:TGOS","URL1":"https://taiwanpork.coa.gov.tw/files/food_data/14532/A01.jpg","URL2":"","URL3":""},"geometry":{"x":121.08095900000001,"y":24.82723500000003}},{"attributes":{"OBJECTID":73445,"market_name":"杰昇黑豬肉","addr":"新竹縣竹北市仁和街60號(竹內市場)","business_week":"星期二,星期三,星期四,星期五,星期六,星期日","context":"自產自銷的好吃黑豬肉","ValidDate":1713801600000,"Lontitude":121.011313,"Latitude":24.837641,"case_code":"2021040700010","created_user":"godspeed","created_date":1619671065000,"last_edited_user":"Developer","last_edited_date":1619996004000,"type":"販售","badge_code":"D005065","business_hours":"05:00","business_hours_end":"00:00","AddrToLonLatProcTime":1620023923000,"AddrToLonLatProcLog":"處理成功:TGOS","URL1":"https://taiwanpork.coa.gov.tw/files/food_data/14573/A01_2.jpg","URL2":"","URL3":""},"geometry":{"x":121.01131300000009,"y":24.837641000000076}},{"attributes":{"OBJECTID":73446,"market_name":"陳先生肉丸水晶餃","addr":"新竹縣竹北市竹仁街24號","business_week":"星期一,星期二,星期三,星期四,星期五,星期六,星期日","context":"粽子 餛飩 水晶餃 肉圓等","ValidDate":1713801600000,"Lontitude":121.009924,"Latitude":24.837064,"case_code":"2021041200027","created_user":"godspeed","created_date":1619671067000,"last_edited_user":"Developer","last_edited_date":1619996004000,"type":"餐飲","badge_code":"D005066","business_hours":"06:00","business_hours_end":"00:30","AddrToLonLatProcTime":1620023923000,"AddrToLonLatProcLog":"處理成功:TGOS","URL1":"https://taiwanpork.coa.gov.tw/files/food_data/14831/A01.jpg","URL2":"","URL3":""},"geometry":{"x":121.00992400000007,"y":24.837064000000055}},{"attributes":{"OBJECTID":73447,"market_name":"陳太太客家米食","addr":"新竹縣竹北市竹仁街24號","business_week":"星期一,星期二,星期三,星期四,星期五,星期六,星期日","context":"粽子 餛飩 水晶餃 肉圓等","ValidDate":1713801600000,"Lontitude":121.009924,"Latitude":24.837064,"case_code":"2021041200031","created_user":"godspeed","created_date":1619671115000,"last_edited_user":"Developer","last_edited_date":1619996004000,"type":"餐飲","badge_code":"D005078","business_hours":"06:00","business_hours_end":"00:30","AddrToLonLatProcTime":1620023923000,"AddrToLonLatProcLog":"處理成功:TGOS","URL1":"https://taiwanpork.coa.gov.tw/files/food_data/14835/A01.jpg","URL2":"","URL3":""},"geometry":{"x":121.00992400000007,"y":24.837064000000055}},{"attributes":{"OBJECTID":73448,"market_name":"卓董生鮮牛羊豬","addr":"新竹縣竹北市仁愛街45號","business_week":"星期一,星期二,星期三,星期四,星期五,星期六,星期日","context":"生鮮豬肉片 均使用台灣豬","ValidDate":1713801600000,"Lontitude":121.010769,"Latitude":24.837299,"case_code":"2021041200036","created_user":"godspeed","created_date":1619671118000,"last_edited_user":"Developer","last_edited_date":1619996004000,"type":"餐飲","badge_code":"D005079","business_hours":"05:00","business_hours_end":"13:00","AddrToLonLatProcTime":1620023923000,"AddrToLonLatProcLog":"處理成功:TGOS","URL1":"https://taiwanpork.coa.gov.tw/files/food_data/14840/A01.jpg","URL2":"","URL3":""},"geometry":{"x":121.0107690000001,"y":24.83729900000003}},{"attributes":{"OBJECTID":73449,"market_name":"李記小籠包","addr":"南投縣南投市民生街41號","business_week":"星期二,星期三,星期四,星期五,星期六,星期日","context":"","ValidDate":1713801600000,"Lontitude":120.684901,"Latitude":23.909813,"case_code":"2021033000075","created_user":"godspeed","created_date":1619671143000,"last_edited_user":"Developer","last_edited_date":1619996004000,"type":"販售","badge_code":"D005083","business_hours":"06:00","business_hours_end":"09:00","AddrToLonLatProcTime":1620023923000,"AddrToLonLatProcLog":"處理成功:TGOS","URL1":"https://taiwanpork.coa.gov.tw/files/food_data/14278/A01.jpg","URL2":"","URL3":""},"geometry":{"x":120.68490100000008,"y":23.909813000000042}},{"attributes":{"OBJECTID":73450,"market_name":"品香小籠包","addr":"南投縣南投市彰南路一段651號","business_week":"星期二,星期三,星期四,星期五,星期六,星期日","context":"本店販售小籠包、饅頭等產品，使用國產豬肉","ValidDate":1713801600000,"Lontitude":120.686633,"Latitude":23.896398,"case_code":"2021033000080","created_user":"godspeed","created_date":1619671145000,"last_edited_user":"Developer","last_edited_date":1619996004000,"type":"餐飲","badge_code":"D005084","business_hours":"06:00","business_hours_end":"11:00","AddrToLonLatProcTime":1620023923000,"AddrToLonLatProcLog":"處理成功:TGOS","URL1":"https://taiwanpork.coa.gov.tw/files/food_data/14283/A01.jpg","URL2":"","URL3":""},"geometry":{"x":120.68663300000003,"y":23.896398000000033}},{"attributes":{"OBJECTID":73451,"market_name":"品麗鹽酥雞","addr":"南投縣魚池鄉魚池街325號","business_week":"星期一,星期二,星期三,星期四,星期五,星期六,星期日","context":"炸排骨、炸肉丸子、炸三層肉","ValidDate":1713801600000,"Lontitude":120.937991,"Latitude":23.89646,"case_code":"2021033000093","created_user":"godspeed","created_date":1619671147000,"last_edited_user":"Developer","last_edited_date":1619996004000,"type":"販售","badge_code":"D005085","business_hours":"18:00","business_hours_end":"23:00","AddrToLonLatProcTime":1620023923000,"AddrToLonLatProcLog":"處理成功:TGOS","URL1":"https://taiwanpork.coa.gov.tw/files/food_data/14296/A01.jpg","URL2":"","URL3":""},"geometry":{"x":120.93799100000001,"y":23.896460000000047}},{"attributes":{"OBJECTID":73452,"market_name":"故鄉味排骨大王","addr":"南投縣名間鄉中正村彰南路30-1號","business_week":"星期一,星期二,星期三,星期四,星期五,星期六","context":"","ValidDate":1713801600000,"Lontitude":120.7034279,"Latitude":23.837468,"case_code":"2021040600034","created_user":"godspeed","created_date":1619671148000,"last_edited_user":"Developer","last_edited_date":1619996004000,"type":"販售","badge_code":"D005086","business_hours":"09:00","business_hours_end":"14:00","AddrToLonLatProcTime":1620023923000,"AddrToLonLatProcLog":"處理成功:Google","URL1":"https://taiwanpork.coa.gov.tw/files/food_data/14527/A01.jpg","URL2":"","URL3":""},"geometry":{"x":120.70342790000007,"y":23.837468000000058}},{"attributes":{"OBJECTID":73453,"market_name":"阿榮火雞肉飯","addr":"南投縣草屯鎮太平路一段99號","business_week":"星期一,星期二,星期三,星期四,星期五,星期日","context":"本店販售火雞肉飯、魯肉、爌肉、豬腳，使用優質國產豬肉","ValidDate":1713801600000,"Lontitude":120.680919,"Latitude":23.958406,"case_code":"2021041200059","created_user":"godspeed","created_date":1619671152000,"last_edited_user":"Developer","last_edited_date":1619996004000,"type":"餐飲","badge_code":"D005089","business_hours":"11:00","business_hours_end":"19:30","AddrToLonLatProcTime":1620023923000,"AddrToLonLatProcLog":"處理成功:TGOS","URL1":"https://taiwanpork.coa.gov.tw/files/food_data/14863/A01.jpg","URL2":"","URL3":""},"geometry":{"x":120.68091900000002,"y":23.958406000000025}},{"attributes":{"OBJECTID":73454,"market_name":"南軒小館","addr":"南投縣集集鎮民生路200-1號","business_week":"星期一,星期三,星期四,星期五,星期六,星期日","context":"熱炒 使用國產豬肉","ValidDate":1713801600000,"Lontitude":120.7838739,"Latitude":23.8271171,"case_code":"2021033000005","created_user":"godspeed","created_date":1619671156000,"last_edited_user":"Developer","last_edited_date":1619996004000,"type":"餐飲","badge_code":"D005082","business_hours":"11:00","business_hours_end":"20:00","AddrToLonLatProcTime":1620023923000,"AddrToLonLatProcLog":"處理成功:Google","URL1":"https://taiwanpork.coa.gov.tw/files/food_data/14208/A01_2.jpg","URL2":"","URL3":""},"geometry":{"x":120.78387390000012,"y":23.827117100000066}},{"attributes":{"OBJECTID":73455,"market_name":"蕙茗園","addr":"嘉義縣梅山鄉瑞里村86號","business_week":"星期一,星期二,星期三,星期四,星期五,星期六,星期日","context":"主要以便當跟合菜(無菜單料理)為主","ValidDate":1713801600000,"Lontitude":120.669843,"Latitude":23.538239,"case_code":"2021040100039","created_user":"godspeed","created_date":1619671200000,"last_edited_user":"Developer","last_edited_date":1619996004000,"type":"餐飲","badge_code":"D005106","business_hours":"10:00","business_hours_end":"18:00","AddrToLonLatProcTime":1620023923000,"AddrToLonLatProcLog":"處理成功:Google","URL1":"https://taiwanpork.coa.gov.tw/files/food_data/14442/A01.jpg","URL2":"","URL3":""},"geometry":{"x":120.66984300000001,"y":23.538239000000033}},{"attributes":{"OBJECTID":73456,"market_name":"瑞里茶壺民宿餐廳","addr":"嘉義縣梅山鄉瑞里村102號","business_week":"星期一,星期三,星期四,星期五,星期六,星期日","context":"","ValidDate":1713801600000,"Lontitude":120.6682128,"Latitude":23.5391529,"case_code":"2021040100047","created_user":"godspeed","created_date":1619671201000,"last_edited_user":"Developer","last_edited_date":1619996004000,"type":"餐飲","badge_code":"D005107","business_hours":"08:00","business_hours_end":"18:30","AddrToLonLatProcTime":1620023923000,"AddrToLonLatProcLog":"處理成功:Google","URL1":"https://taiwanpork.coa.gov.tw/files/food_data/14450/A01.jpg","URL2":"","URL3":""},"geometry":{"x":120.66821280000011,"y":23.539152900000033}},{"attributes":{"OBJECTID":73457,"market_name":"生力農場","addr":"嘉義縣番路鄉公田村003鄰隙頂9-5號","business_week":"星期一,星期二,星期三,星期四,星期五,星期六,星期日","context":"生力農場經營民宿、餐廳、製茶廠","ValidDate":1713801600000,"Lontitude":120.6643359,"Latitude":23.431723,"case_code":"2021040700053","created_user":"godspeed","created_date":1619671206000,"last_edited_user":"Developer","last_edited_date":1619996004000,"type":"餐飲","badge_code":"D005108","business_hours":"10:00","business_hours_end":"20:00","AddrToLonLatProcTime":1620023923000,"AddrToLonLatProcLog":"處理成功:Google","URL1":"https://taiwanpork.coa.gov.tw/files/food_data/14617/A01.jpg","URL2":"","URL3":""},"geometry":{"x":120.66433590000008,"y":23.431723000000034}},{"attributes":{"OBJECTID":73458,"market_name":"山賓餐廳","addr":"嘉義縣阿里山鄉東阿里山19號","business_week":"星期一,星期二,星期三,星期四,星期五,星期六,星期日","context":"本店販售火鍋、熱炒、合菜等產品，全部都使用台灣豬肉","ValidDate":1713801600000,"Lontitude":120.7135217,"Latitude":23.4712117,"case_code":"2021040700063","created_user":"godspeed","created_date":1619671219000,"last_edited_user":"Developer","last_edited_date":1619996004000,"type":"餐飲","badge_code":"D005111","business_hours":"10:30","business_hours_end":"20:30","AddrToLonLatProcTime":1620023923000,"AddrToLonLatProcLog":"處理成功:Google","URL1":"https://taiwanpork.coa.gov.tw/files/food_data/14627/A01.jpg","URL2":"","URL3":""},"geometry":{"x":120.71352170000011,"y":23.471211700000026}},{"attributes":{"OBJECTID":73459,"market_name":"九九九餐飲部","addr":"嘉義縣阿里山鄉東阿里山10號","business_week":"星期一,星期二,星期三,星期四,星期五,星期六,星期日","context":"本店販售飯、麵、熱炒、火鍋等產品，全部都使用國產豬肉","ValidDate":1713801600000,"Lontitude":120.667108,"Latitude":23.386124,"case_code":"2021040700068","created_user":"godspeed","created_date":1619671221000,"last_edited_user":"Developer","last_edited_date":1619996004000,"type":"餐飲","badge_code":"D005112","business_hours":"10:30","business_hours_end":"20:00","AddrToLonLatProcTime":1620023923000,"AddrToLonLatProcLog":"處理成功:Google","URL1":"https://taiwanpork.coa.gov.tw/files/food_data/14632/A01.jpg","URL2":"","URL3":""},"geometry":{"x":120.6671080000001,"y":23.386124000000052}},{"attributes":{"OBJECTID":73460,"market_name":"信記燒烤海鮮","addr":"宜蘭縣頭城鎮濱海路五段500號","business_week":"星期一,星期二,星期三,星期四,星期五,星期六,星期日","context":"海鮮快炒 肉絲國產豬","ValidDate":1713110400000,"Lontitude":121.901945,"Latitude":24.941478,"case_code":"2021032400018","created_user":"godspeed","created_date":1619982099000,"last_edited_user":"Developer","last_edited_date":1619996004000,"type":"餐飲","badge_code":"B002602","business_hours":"00:00","business_hours_end":"06:00","AddrToLonLatProcTime":1620023923000,"AddrToLonLatProcLog":"處理成功:TGOS","URL1":"https://taiwanpork.coa.gov.tw/files/food_data/13770/A01.jpg","URL2":"","URL3":""},"geometry":{"x":121.90194500000007,"y":24.941478000000075}},{"attributes":{"OBJECTID":73461,"market_name":"東旅湯宿","addr":"宜蘭縣礁溪鄉信義路32號","business_week":"星期一,星期二,星期三,星期四,星期五,星期六,星期日","context":"","ValidDate":1713110400000,"Lontitude":121.770503,"Latitude":24.826322,"case_code":"2021032400072","created_user":"godspeed","created_date":1619982108000,"last_edited_user":"Developer","last_edited_date":1619996004000,"type":"餐飲","badge_code":"B002603","business_hours":"08:00","business_hours_end":"21:00","AddrToLonLatProcTime":1620023923000,"AddrToLonLatProcLog":"處理成功:TGOS","URL1":"https://taiwanpork.coa.gov.tw/files/food_data/13824/A01.jpg","URL2":"","URL3":""},"geometry":{"x":121.77050300000008,"y":24.826322000000062}},{"attributes":{"OBJECTID":73462,"market_name":"波卡拉渡假會館","addr":"宜蘭縣礁溪鄉茅埔路3號","business_week":"星期一,星期二,星期三,星期四,星期五,星期六,星期日","context":"","ValidDate":1713110400000,"Lontitude":121.7916171,"Latitude":24.7961472,"case_code":"2021032400075","created_user":"godspeed","created_date":1619982112000,"last_edited_user":"Developer","last_edited_date":1619996030000,"type":"餐飲","badge_code":"B002604","business_hours":"08:30","business_hours_end":"21:00","AddrToLonLatProcTime":1620023923000,"AddrToLonLatProcLog":"處理成功:Google","URL1":"https://taiwanpork.coa.gov.tw/files/food_data/13827/A01.jpg","URL2":"","URL3":""},"geometry":{"x":121.79161710000005,"y":24.796147200000064}},{"attributes":{"OBJECTID":73463,"market_name":"東旅湯宿風華漾","addr":"宜蘭縣礁溪鄉德陽路28號","business_week":"星期一,星期二,星期三,星期四,星期五,星期六,星期日","context":"用天然溫泉與日式建築圍繞一甲子的老靈魂，以民宿的溫度、飯店的品質，創造出療癒身心靈的旅宿空間","ValidDate":1713110400000,"Lontitude":121.7719488,"Latitude":24.8286651,"case_code":"2021032400078","created_user":"godspeed","created_date":1619982115000,"last_edited_user":"Developer","last_edited_date":1619996030000,"type":"餐飲","badge_code":"B002605","business_hours":"00:00","business_hours_end":"00:00","AddrToLonLatProcTime":1620023923000,"AddrToLonLatProcLog":"處理成功:Google","URL1":"https://taiwanpork.coa.gov.tw/files/food_data/13830/A01.jpg","URL2":"","URL3":""},"geometry":{"x":121.77194880000002,"y":24.828665100000023}},{"attributes":{"OBJECTID":73464,"market_name":"員山鄉三興廟","addr":"宜蘭縣員山鄉深洲二路235-5號","business_week":"星期一,星期二,星期三,星期四,星期五","context":"長青食堂用餐","ValidDate":1713110400000,"Lontitude":121.7165934,"Latitude":24.7089131,"case_code":"2021032500025","created_user":"godspeed","created_date":1619982120000,"last_edited_user":"Developer","last_edited_date":1619996030000,"type":"餐飲","badge_code":"B002606","business_hours":"12:00","business_hours_end":"20:00","AddrToLonLatProcTime":1620023923000,"AddrToLonLatProcLog":"處理成功:Google","URL1":"https://taiwanpork.coa.gov.tw/files/food_data/13906/A01.jpg","URL2":"","URL3":""},"geometry":{"x":121.71659340000008,"y":24.708913100000075}},{"attributes":{"OBJECTID":73465,"market_name":"上讚麵民生店","addr":"宜蘭縣羅東鎮民生路150號","business_week":"星期二,星期三,星期四,星期五,星期六,星期日","context":"本店販售麵、湯類等產品","ValidDate":1713110400000,"Lontitude":121.765191,"Latitude":24.678197,"case_code":"2021032500081","created_user":"godspeed","created_date":1619982169000,"last_edited_user":"Developer","last_edited_date":1619996030000,"type":"餐飲","badge_code":"C003042","business_hours":"07:00","business_hours_end":"13:30","AddrToLonLatProcTime":1620023923000,"AddrToLonLatProcLog":"處理成功:TGOS","URL1":"https://taiwanpork.coa.gov.tw/files/food_data/13962/A01.jpg","URL2":"","URL3":""},"geometry":{"x":121.76519100000007,"y":24.678197000000068}},{"attributes":{"OBJECTID":73466,"market_name":" 泰錝泰式料理店(羅東店)","addr":"宜蘭縣羅東鎮南豪里興東南路73號1樓","business_week":"星期一,星期二,星期三,星期四,星期五,星期六,星期日","context":"泰式料理   ","ValidDate":1713110400000,"Lontitude":121.769964,"Latitude":24.669743,"case_code":"2021032300015","created_user":"godspeed","created_date":1619982198000,"last_edited_user":"Developer","last_edited_date":1619996031000,"type":"餐飲","badge_code":"D004519","business_hours":"11:30","business_hours_end":"21:00","AddrToLonLatProcTime":1620023923000,"AddrToLonLatProcLog":"處理成功:TGOS","URL1":"https://taiwanpork.coa.gov.tw/files/food_data/13655/A01.jpg","URL2":"","URL3":""},"geometry":{"x":121.76996400000007,"y":24.66974300000004}},{"attributes":{"OBJECTID":73467,"market_name":"泰錝(宜蘭店)","addr":"宜蘭縣宜蘭市建業里公園路483號1樓","business_week":"星期一,星期二,星期三,星期四,星期五,星期六,星期日","context":"泰式料理    ","ValidDate":1713110400000,"Lontitude":121.755529,"Latitude":24.741226,"case_code":"2021032300016","created_user":"godspeed","created_date":1619982212000,"last_edited_user":"Developer","last_edited_date":1619996031000,"type":"餐飲","badge_code":"D004520","business_hours":"11:30","business_hours_end":"21:00","AddrToLonLatProcTime":1620023923000,"AddrToLonLatProcLog":"處理成功:TGOS","URL1":"https://taiwanpork.coa.gov.tw/files/food_data/13656/A01.jpg","URL2":"","URL3":""},"geometry":{"x":121.75552900000002,"y":24.74122600000004}},{"attributes":{"OBJECTID":73468,"market_name":"成功包子店","addr":"宜蘭縣羅東鎮成功里007鄰南門路43號一樓","business_week":"星期一,星期二,星期三,星期四,星期五,星期六,星期日","context":"本店販售各式包子等，使用優質國產豬肉","ValidDate":1713110400000,"Lontitude":121.7688161,"Latitude":24.6726829,"case_code":"2021032300060","created_user":"godspeed","created_date":1619982214000,"last_edited_user":"Developer","last_edited_date":1619996031000,"type":"販售","badge_code":"D004521","business_hours":"06:30","business_hours_end":"11:00","AddrToLonLatProcTime":1620023923000,"AddrToLonLatProcLog":"處理成功:Google","URL1":"https://taiwanpork.coa.gov.tw/files/food_data/13700/A01.jpg","URL2":"","URL3":""},"geometry":{"x":121.76881610000009,"y":24.672682900000041}},{"attributes":{"OBJECTID":73469,"market_name":"亭Y 腳精緻麵食館","addr":"宜蘭縣羅東鎮公正路333號一樓","business_week":"星期一,星期二,星期三,星期四,星期五,星期六","context":"本店販售便當","ValidDate":1713110400000,"Lontitude":121.762163,"Latitude":24.680389,"case_code":"2021032300064","created_user":"godspeed","created_date":1619982216000,"last_edited_user":"Developer","last_edited_date":1619996031000,"type":"餐飲","badge_code":"D004522","business_hours":"10:00","business_hours_end":"20:00","AddrToLonLatProcTime":1620023923000,"AddrToLonLatProcLog":"處理成功:TGOS","URL1":"https://taiwanpork.coa.gov.tw/files/food_data/13704/A01.jpg","URL2":"","URL3":""},"geometry":{"x":121.7621630000001,"y":24.680389000000048}},{"attributes":{"OBJECTID":73470,"market_name":"正常鮮肉小籠湯包","addr":"宜蘭縣羅東鎮成功里南門路7號1樓","business_week":"星期一,星期二,星期三,星期四,星期五,星期六,星期日","context":"本店販售鮮肉小湯包","ValidDate":1713110400000,"Lontitude":121.769889,"Latitude":24.672587,"case_code":"2021032300067","created_user":"godspeed","created_date":1619982217000,"last_edited_user":"Developer","last_edited_date":1619996031000,"type":"餐飲","badge_code":"D004523","business_hours":"06:10","business_hours_end":"13:30","AddrToLonLatProcTime":1620023923000,"AddrToLonLatProcLog":"處理成功:TGOS","URL1":"https://taiwanpork.coa.gov.tw/files/food_data/13707/A01.jpg","URL2":"","URL3":""},"geometry":{"x":121.76988900000003,"y":24.672587000000078}},{"attributes":{"OBJECTID":73471,"market_name":"市場口水餃店","addr":"宜蘭縣羅東鎮培英路100-3號","business_week":"星期二,星期三,星期四,星期五,星期六,星期日","context":"水餃專賣店，販售麵食、小菜等","ValidDate":1713110400000,"Lontitude":121.759582,"Latitude":24.6784075,"case_code":"2021032300078","created_user":"godspeed","created_date":1619982219000,"last_edited_user":"Developer","last_edited_date":1619996031000,"type":"餐飲","badge_code":"D004524","business_hours":"10:00","business_hours_end":"21:00","AddrToLonLatProcTime":1620023923000,"AddrToLonLatProcLog":"處理成功:Google","URL1":"https://taiwanpork.coa.gov.tw/files/food_data/13718/A01.jpg","URL2":"","URL3":""},"geometry":{"x":121.75958200000002,"y":24.678407500000048}},{"attributes":{"OBJECTID":73472,"market_name":"佐食坊","addr":"宜蘭縣羅東鎮中華路78-2號","business_week":"星期二,星期三,星期四,星期五,星期六,星期日","context":"本店販售各式麵、湯類產品","ValidDate":1713110400000,"Lontitude":121.7673307,"Latitude":24.6789538,"case_code":"2021032300082","created_user":"godspeed","created_date":1619982220000,"last_edited_user":"Developer","last_edited_date":1619996031000,"type":"餐飲","badge_code":"D004525","business_hours":"11:00","business_hours_end":"21:30","AddrToLonLatProcTime":1620023923000,"AddrToLonLatProcLog":"處理成功:Google","URL1":"https://taiwanpork.coa.gov.tw/files/food_data/13722/A01_2.jpg","URL2":"","URL3":""},"geometry":{"x":121.76733070000012,"y":24.678953800000045}},{"attributes":{"OBJECTID":73473,"market_name":"羅東碳烤燒餅店","addr":"宜蘭縣羅東鎮南門路32號","business_week":"星期一,星期二,星期三,星期四,星期五,星期六","context":"鎮內知名燒餅店,使用優質國產豬肉","ValidDate":1713110400000,"Lontitude":121.76908,"Latitude":24.673009,"case_code":"2021032400010","created_user":"godspeed","created_date":1619982230000,"last_edited_user":"Developer","last_edited_date":1619996031000,"type":"販售","badge_code":"D004526","business_hours":"08:00","business_hours_end":"17:30","AddrToLonLatProcTime":1620023923000,"AddrToLonLatProcLog":"處理成功:TGOS","URL1":"https://taiwanpork.coa.gov.tw/files/food_data/13762/A01.jpg","URL2":"","URL3":""},"geometry":{"x":121.76908000000003,"y":24.673009000000036}},{"attributes":{"OBJECTID":73474,"market_name":"菊妹牛莊","addr":"宜蘭縣冬山鄉冬山路81號","business_week":"星期一,星期二,星期三,星期四,星期五,星期六,星期日","context":"經營菊妹牛排館","ValidDate":1713110400000,"Lontitude":121.793439,"Latitude":24.633424,"case_code":"2021032400012","created_user":"godspeed","created_date":1619982232000,"last_edited_user":"Developer","last_edited_date":1619996031000,"type":"餐飲","badge_code":"D004527","business_hours":"11:00","business_hours_end":"21:00","AddrToLonLatProcTime":1620023923000,"AddrToLonLatProcLog":"處理成功:TGOS","URL1":"https://taiwanpork.coa.gov.tw/files/food_data/13764/A01.jpg","URL2":"","URL3":""},"geometry":{"x":121.79343900000003,"y":24.633424000000048}},{"attributes":{"OBJECTID":73475,"market_name":"加一鍋日式涮涮鍋","addr":"宜蘭縣冬山鄉永興路一段79號","business_week":"星期一,星期三,星期四,星期五,星期六,星期日","context":"本店販售涮涮鍋","ValidDate":1713110400000,"Lontitude":121.775599,"Latitude":24.655003,"case_code":"2021032400026","created_user":"godspeed","created_date":1619982233000,"last_edited_user":"Developer","last_edited_date":1619996031000,"type":"餐飲","badge_code":"D004528","business_hours":"11:00","business_hours_end":"20:00","AddrToLonLatProcTime":1620023923000,"AddrToLonLatProcLog":"處理成功:TGOS","URL1":"https://taiwanpork.coa.gov.tw/files/food_data/13778/A01.jpg","URL2":"","URL3":""},"geometry":{"x":121.77559900000006,"y":24.655003000000079}},{"attributes":{"OBJECTID":73476,"market_name":" 鑫美麵食坊","addr":"宜蘭縣羅東鎮中華路146號","business_week":"星期一,星期二,星期三,星期四,星期五,星期六,星期日","context":"本店賣餛飩 肉燥 使用台灣豬","ValidDate":1713110400000,"Lontitude":121.76799,"Latitude":24.680983,"case_code":"2021032400056","created_user":"godspeed","created_date":1619982234000,"last_edited_user":"Developer","last_edited_date":1619996031000,"type":"餐飲","badge_code":"D004529","business_hours":"06:30","business_hours_end":"18:30","AddrToLonLatProcTime":1620023923000,"AddrToLonLatProcLog":"處理成功:TGOS","URL1":"https://taiwanpork.coa.gov.tw/files/food_data/13808/A01.jpg","URL2":"","URL3":""},"geometry":{"x":121.76799000000005,"y":24.680983000000026}},{"attributes":{"OBJECTID":73477,"market_name":"來一客牛排館","addr":"宜蘭縣羅東鎮民生東路33號","business_week":"星期一,星期二,星期三,星期五,星期六,星期日","context":"本店販售豬排、豬肉炒飯等，使用優質國產豬肉","ValidDate":1713110400000,"Lontitude":121.773072,"Latitude":24.675712,"case_code":"2021032400057","created_user":"godspeed","created_date":1619982252000,"last_edited_user":"Developer","last_edited_date":1619996031000,"type":"餐飲","badge_code":"D004530","business_hours":"11:00","business_hours_end":"20:00","AddrToLonLatProcTime":1620023923000,"AddrToLonLatProcLog":"處理成功:TGOS","URL1":"https://taiwanpork.coa.gov.tw/files/food_data/13809/A01.jpg","URL2":"","URL3":""},"geometry":{"x":121.77307200000007,"y":24.675712000000033}},{"attributes":{"OBJECTID":73478,"market_name":"五結頂好快炒","addr":"宜蘭縣五結鄉五結路二段506號","business_week":"星期一,星期二,星期三,星期四,星期五,星期六,星期日","context":"販售面、飯類，使用排骨、梅花、五花等國產豬","ValidDate":1713110400000,"Lontitude":121.795629,"Latitude":24.684588,"case_code":"2021032400062","created_user":"godspeed","created_date":1619982254000,"last_edited_user":"Developer","last_edited_date":1619996031000,"type":"餐飲","badge_code":"D004531","business_hours":"18:00","business_hours_end":"23:30","AddrToLonLatProcTime":1620023923000,"AddrToLonLatProcLog":"處理成功:TGOS","URL1":"https://taiwanpork.coa.gov.tw/files/food_data/13814/A01.jpg","URL2":"","URL3":""},"geometry":{"x":121.79562900000008,"y":24.684588000000076}},{"attributes":{"OBJECTID":73479,"market_name":"吉得堡早餐店","addr":"宜蘭縣員山鄉惠民路289號","business_week":"星期二,星期三,星期四,星期五,星期六,星期日","context":"本店販售豬肉漢堡、吐司","ValidDate":1713110400000,"Lontitude":121.723072,"Latitude":24.722933,"case_code":"2021032400071","created_user":"godspeed","created_date":1619982257000,"last_edited_user":"Developer","last_edited_date":1619996031000,"type":"販售","badge_code":"D004532","business_hours":"05:30","business_hours_end":"00:00","AddrToLonLatProcTime":1620023923000,"AddrToLonLatProcLog":"處理成功:TGOS","URL1":"https://taiwanpork.coa.gov.tw/files/food_data/13823/A01.jpg","URL2":"","URL3":""},"geometry":{"x":121.72307200000012,"y":24.722933000000069}},{"attributes":{"OBJECTID":73480,"market_name":"樹人路麵攤","addr":"宜蘭縣羅東鎮樹人路72號","business_week":"星期一,星期三,星期四,星期五,星期六,星期日","context":"本店販售餛飩麵 焢肉飯 蛋餅 紅茶等產品","ValidDate":1713110400000,"Lontitude":121.764281,"Latitude":24.682734,"case_code":"2021032400077","created_user":"godspeed","created_date":1619982258000,"last_edited_user":"Developer","last_edited_date":1619996031000,"type":"餐飲","badge_code":"D004533","business_hours":"06:00","business_hours_end":"13:00","AddrToLonLatProcTime":1620023923000,"AddrToLonLatProcLog":"處理成功:TGOS","URL1":"https://taiwanpork.coa.gov.tw/files/food_data/13829/A01.jpg","URL2":"","URL3":""},"geometry":{"x":121.7642810000001,"y":24.682734000000039}},{"attributes":{"OBJECTID":73481,"market_name":"丼屋食堂","addr":"宜蘭縣羅東鎮中山路四段55號","business_week":"星期二,星期三,星期四,星期五,星期六,星期日","context":"本店販售日式便當炸豬排、叉燒便當等商品，使用優質國產豬肉","ValidDate":1713110400000,"Lontitude":121.762298,"Latitude":24.673857,"case_code":"2021032400080","created_user":"godspeed","created_date":1619982259000,"last_edited_user":"Developer","last_edited_date":1619996031000,"type":"餐飲","badge_code":"D004534","business_hours":"11:00","business_hours_end":"20:00","AddrToLonLatProcTime":1620023923000,"AddrToLonLatProcLog":"處理成功:TGOS","URL1":"https://taiwanpork.coa.gov.tw/files/food_data/13832/A01.jpg","URL2":"","URL3":""},"geometry":{"x":121.7622980000001,"y":24.673857000000055}},{"attributes":{"OBJECTID":73482,"market_name":" 八分煲咖啡簡餐","addr":"宜蘭縣羅東鎮北成路一段166號","business_week":"星期一,星期三,星期四,星期五,星期六,星期日","context":"本店販售麵、簡餐、小火鍋","ValidDate":1713110400000,"Lontitude":121.758463,"Latitude":24.675961,"case_code":"2021032400083","created_user":"godspeed","created_date":1619982261000,"last_edited_user":"Developer","last_edited_date":1619996031000,"type":"餐飲","badge_code":"D004535","business_hours":"11:30","business_hours_end":"20:30","AddrToLonLatProcTime":1620023923000,"AddrToLonLatProcLog":"處理成功:TGOS","URL1":"https://taiwanpork.coa.gov.tw/files/food_data/13835/A01.jpg","URL2":"","URL3":""},"geometry":{"x":121.75846300000001,"y":24.675961000000029}},{"attributes":{"OBJECTID":73483,"market_name":"芳香","addr":"宜蘭縣羅東鎮愛國路252號","business_week":"星期一,星期二,星期三,星期四,星期五,星期六","context":"店內賣蚵仔煎、肉絲炒麵、海鮮粥等","ValidDate":1713110400000,"Lontitude":121.765478,"Latitude":24.679955,"case_code":"2021032400085","created_user":"godspeed","created_date":1619982262000,"last_edited_user":"Developer","last_edited_date":1619996031000,"type":"餐飲","badge_code":"D004536","business_hours":"11:30","business_hours_end":"20:00","AddrToLonLatProcTime":1620023923000,"AddrToLonLatProcLog":"處理成功:TGOS","URL1":"https://taiwanpork.coa.gov.tw/files/food_data/13837/A01.jpg","URL2":"","URL3":""},"geometry":{"x":121.76547800000003,"y":24.679955000000064}},{"attributes":{"OBJECTID":73484,"market_name":"加州牛排店","addr":"宜蘭縣羅東鎮中華路20號","business_week":"星期一,星期三,星期四,星期五,星期六,星期日","context":"本店販售豬、牛、雞排餐(鐵板)","ValidDate":1713110400000,"Lontitude":121.766274,"Latitude":24.675666,"case_code":"2021032400088","created_user":"godspeed","created_date":1619982263000,"last_edited_user":"Developer","last_edited_date":1619996032000,"type":"餐飲","badge_code":"D004537","business_hours":"16:00","business_hours_end":"22:00","AddrToLonLatProcTime":1620023923000,"AddrToLonLatProcLog":"處理成功:TGOS","URL1":"https://taiwanpork.coa.gov.tw/files/food_data/13840/A01.jpg","URL2":"","URL3":""},"geometry":{"x":121.76627400000007,"y":24.675666000000035}},{"attributes":{"OBJECTID":73485,"market_name":"香香食坊","addr":"宜蘭縣羅東鎮復興路二段282號","business_week":"星期一,星期二,星期四,星期五,星期六,星期日","context":"本店販售麵、飯、小菜等產品,使用優質國產豬肉","ValidDate":1713110400000,"Lontitude":121.764216,"Latitude":24.691279,"case_code":"2021032400093","created_user":"godspeed","created_date":1619982265000,"last_edited_user":"Developer","last_edited_date":1619996032000,"type":"餐飲","badge_code":"D004539","business_hours":"06:00","business_hours_end":"14:00","AddrToLonLatProcTime":1620023923000,"AddrToLonLatProcLog":"處理成功:TGOS","URL1":"https://taiwanpork.coa.gov.tw/files/food_data/13845/A01.jpg","URL2":"","URL3":""},"geometry":{"x":121.76421600000003,"y":24.691279000000065}},{"attributes":{"OBJECTID":73486,"market_name":"福記排骨酥麵","addr":"宜蘭縣羅東鎮中華路114號","business_week":"星期一,星期二,星期三,星期四,星期五,星期六","context":"","ValidDate":1713110400000,"Lontitude":121.767781,"Latitude":24.680299,"case_code":"2021032400091","created_user":"godspeed","created_date":1619982266000,"last_edited_user":"Developer","last_edited_date":1619996032000,"type":"餐飲","badge_code":"D004538","business_hours":"11:00","business_hours_end":"19:00","AddrToLonLatProcTime":1620023923000,"AddrToLonLatProcLog":"處理成功:TGOS","URL1":"https://taiwanpork.coa.gov.tw/files/food_data/13843/A01.jpg","URL2":"","URL3":""},"geometry":{"x":121.76778100000001,"y":24.680299000000048}},{"attributes":{"OBJECTID":73487,"market_name":"香和牛排(羅東)","addr":"宜蘭縣羅東鎮中山路二段356號","business_week":"星期一,星期二,星期三,星期四,星期五,星期六,星期日","context":"本店販售牛、豬、雞排","ValidDate":1713110400000,"Lontitude":121.77842,"Latitude":24.674517,"case_code":"2021032400095","created_user":"godspeed","created_date":1619982282000,"last_edited_user":"Developer","last_edited_date":1619996032000,"type":"餐飲","badge_code":"D004540","business_hours":"11:00","business_hours_end":"21:00","AddrToLonLatProcTime":1620023923000,"AddrToLonLatProcLog":"處理成功:TGOS","URL1":"https://taiwanpork.coa.gov.tw/files/food_data/13847/A01.jpg","URL2":"","URL3":""},"geometry":{"x":121.7784200000001,"y":24.674517000000037}},{"attributes":{"OBJECTID":73488,"market_name":"香和牛排(冬山)","addr":"宜蘭縣冬山鄉冬山路一段850號","business_week":"星期一,星期二,星期三,星期四,星期五,星期六,星期日","context":"本店販售牛、豬、雞排","ValidDate":1713110400000,"Lontitude":121.796942,"Latitude":24.631267,"case_code":"2021032400097","created_user":"godspeed","created_date":1619982296000,"last_edited_user":"Developer","last_edited_date":1619996032000,"type":"餐飲","badge_code":"D004541","business_hours":"11:00","business_hours_end":"21:00","AddrToLonLatProcTime":1620023923000,"AddrToLonLatProcLog":"處理成功:TGOS","URL1":"https://taiwanpork.coa.gov.tw/files/food_data/13849/A01.jpg","URL2":"","URL3":""},"geometry":{"x":121.79694200000006,"y":24.631267000000037}},{"attributes":{"OBJECTID":73489,"market_name":"幸福麵攤小吃","addr":"宜蘭縣羅東鎮公正路311號","business_week":"星期二,星期三,星期四,星期五,星期六,星期日","context":"自營小吃部   ","ValidDate":1713110400000,"Lontitude":121.762626,"Latitude":24.680456,"case_code":"2021032400099","created_user":"godspeed","created_date":1619982297000,"last_edited_user":"Developer","last_edited_date":1619996032000,"type":"餐飲","badge_code":"D004542","business_hours":"11:00","business_hours_end":"20:00","AddrToLonLatProcTime":1620023923000,"AddrToLonLatProcLog":"處理成功:TGOS","URL1":"https://taiwanpork.coa.gov.tw/files/food_data/13851/A01.jpg","URL2":"","URL3":""},"geometry":{"x":121.76262600000007,"y":24.680456000000049}},{"attributes":{"OBJECTID":73490,"market_name":"山頂會館","addr":"宜蘭縣員山鄉枕山村8鄰枕山一村19號","business_week":"星期一,星期二,星期三,星期四,星期五,星期六,星期日","context":"大型婚宴景觀餐廳","ValidDate":1713110400000,"Lontitude":121.722017,"Latitude":24.7703135,"case_code":"2021032400101","created_user":"godspeed","created_date":1619982298000,"last_edited_user":"Developer","last_edited_date":1619996032000,"type":"餐飲","badge_code":"D004543","business_hours":"11:00","business_hours_end":"20:00","AddrToLonLatProcTime":1620023923000,"AddrToLonLatProcLog":"處理成功:Google","URL1":"https://taiwanpork.coa.gov.tw/files/food_data/13853/A01.jpg","URL2":"","URL3":""},"geometry":{"x":121.72201700000005,"y":24.770313500000043}},{"attributes":{"OBJECTID":73491,"market_name":"和平關東煮","addr":"宜蘭縣羅東鎮大新里和平路170號1樓","business_week":"星期一,星期三,星期四,星期五,星期六,星期日","context":"販售天婦羅、關東煮、鮮蚵大腸麵線等熱食產品\u003cbr /\u003e\r\n","ValidDate":1713110400000,"Lontitude":121.772775,"Latitude":24.677796,"case_code":"2021032400104","created_user":"godspeed","created_date":1619982300000,"last_edited_user":"Developer","last_edited_date":1619996032000,"type":"餐飲","badge_code":"D004545","business_hours":"10:30","business_hours_end":"20:30","AddrToLonLatProcTime":1620023923000,"AddrToLonLatProcLog":"處理成功:TGOS","URL1":"https://taiwanpork.coa.gov.tw/files/food_data/13856/A01.jpg","URL2":"","URL3":""},"geometry":{"x":121.77277500000002,"y":24.677796000000058}},{"attributes":{"OBJECTID":73492,"market_name":"伊丼食堂","addr":"宜蘭縣羅東鎮公正里林森路155號1樓","business_week":"星期一,星期二,星期四,星期五,星期六,星期日","context":"丼飯 簡餐店","ValidDate":1713110400000,"Lontitude":121.766874,"Latitude":24.680154,"case_code":"2021032400102","created_user":"godspeed","created_date":1619982301000,"last_edited_user":"Developer","last_edited_date":1619996032000,"type":"餐飲","badge_code":"D004544","business_hours":"11:00","business_hours_end":"20:00","AddrToLonLatProcTime":1620023923000,"AddrToLonLatProcLog":"處理成功:TGOS","URL1":"https://taiwanpork.coa.gov.tw/files/food_data/13854/A01.jpg","URL2":"","URL3":""},"geometry":{"x":121.76687400000003,"y":24.680154000000073}},{"attributes":{"OBJECTID":73493,"market_name":"羅高早餐店","addr":"宜蘭縣羅東鎮賢文里18鄰公正路331號","business_week":"星期一,星期二,星期三,星期四,星期五,星期六","context":"早餐店          ","ValidDate":1713110400000,"Lontitude":121.76204,"Latitude":24.6803098,"case_code":"2021032400105","created_user":"godspeed","created_date":1619982303000,"last_edited_user":"Developer","last_edited_date":1619996032000,"type":"餐飲","badge_code":"D004546","business_hours":"05:30","business_hours_end":"14:00","AddrToLonLatProcTime":1620023923000,"AddrToLonLatProcLog":"處理成功:Google","URL1":"https://taiwanpork.coa.gov.tw/files/food_data/13857/A01.jpg","URL2":"","URL3":""},"geometry":{"x":121.76204000000007,"y":24.680309800000032}},{"attributes":{"OBJECTID":73494,"market_name":"名軒自助涮涮鍋","addr":"宜蘭縣羅東鎮竹林里純精路3段316號1樓","business_week":"星期一,星期二,星期三,星期四,星期五,星期六,星期日","context":"本店販賣各式飯、麵餐點等產品,使用優質國產豬肉","ValidDate":1713110400000,"Lontitude":121.767129,"Latitude":24.685179,"case_code":"2021032400108","created_user":"godspeed","created_date":1619982304000,"last_edited_user":"Developer","last_edited_date":1619996033000,"type":"餐飲","badge_code":"D004548","business_hours":"10:00","business_hours_end":"22:00","AddrToLonLatProcTime":1620023923000,"AddrToLonLatProcLog":"處理成功:TGOS","URL1":"https://taiwanpork.coa.gov.tw/files/food_data/13860/A01.jpg","URL2":"","URL3":""},"geometry":{"x":121.76712900000007,"y":24.685179000000062}},{"attributes":{"OBJECTID":73495,"market_name":"紅瓦厝","addr":"宜蘭縣羅東鎮仁德里南門路126號1樓","business_week":"星期一,星期二,星期三,星期四,星期五,星期六,星期日","context":"本店販售麻醬麵、乾麵、油飯等熱食產品。(本店每月第一、三個周日店休)","ValidDate":1713110400000,"Lontitude":121.766075,"Latitude":24.673068,"case_code":"2021032400106","created_user":"godspeed","created_date":1619982306000,"last_edited_user":"Developer","last_edited_date":1619996033000,"type":"餐飲","badge_code":"D004547","business_hours":"06:30","business_hours_end":"19:30","AddrToLonLatProcTime":1620023923000,"AddrToLonLatProcLog":"處理成功:TGOS","URL1":"https://taiwanpork.coa.gov.tw/files/food_data/13858/A01.jpg","URL2":"","URL3":""},"geometry":{"x":121.76607500000011,"y":24.673068000000058}},{"attributes":{"OBJECTID":73496,"market_name":"一心拉麵","addr":"宜蘭縣羅東鎮光榮路413號","business_week":"星期一,星期二,星期四,星期五,星期六,星期日","context":"","ValidDate":1713110400000,"Lontitude":121.77188,"Latitude":24.669018,"case_code":"2021032400110","created_user":"godspeed","created_date":1619982307000,"last_edited_user":"Developer","last_edited_date":1619996033000,"type":"餐飲","badge_code":"D004549","business_hours":"11:30","business_hours_end":"21:00","AddrToLonLatProcTime":1620023923000,"AddrToLonLatProcLog":"處理成功:TGOS","URL1":"https://taiwanpork.coa.gov.tw/files/food_data/13862/A01.jpg","URL2":"","URL3":""},"geometry":{"x":121.77188000000001,"y":24.669018000000051}},{"attributes":{"OBJECTID":73497,"market_name":"丞品越南牛肉河粉","addr":"宜蘭縣冬山鄉義成路三段560號","business_week":"星期一,星期二,星期三,星期四,星期五,星期六","context":"越南河粉小吃專賣店","ValidDate":1713110400000,"Lontitude":121.768652,"Latitude":24.669087,"case_code":"2021032400111","created_user":"godspeed","created_date":1619982321000,"last_edited_user":"Developer","last_edited_date":1619996033000,"type":"餐飲","badge_code":"D004550","business_hours":"11:00","business_hours_end":"21:00","AddrToLonLatProcTime":1620023923000,"AddrToLonLatProcLog":"處理成功:TGOS","URL1":"https://taiwanpork.coa.gov.tw/files/food_data/13863/A01.jpg","URL2":"","URL3":""},"geometry":{"x":121.76865200000009,"y":24.669087000000047}},{"attributes":{"OBJECTID":73498,"market_name":"尚好吃麵攤","addr":"宜蘭縣羅東鎮中正南路212號","business_week":"星期一,星期二,星期三,星期四,星期五,星期六,星期日","context":"本店專賣魷魚焿、肉焿等","ValidDate":1713110400000,"Lontitude":121.770363,"Latitude":24.672207,"case_code":"2021032400112","created_user":"godspeed","created_date":1619982331000,"last_edited_user":"Developer","last_edited_date":1619996033000,"type":"餐飲","badge_code":"D004551","business_hours":"10:00","business_hours_end":"20:00","AddrToLonLatProcTime":1620023923000,"AddrToLonLatProcLog":"處理成功:TGOS","URL1":"https://taiwanpork.coa.gov.tw/files/food_data/13864/A01.jpg","URL2":"","URL3":""},"geometry":{"x":121.77036300000009,"y":24.672207000000071}},{"attributes":{"OBJECTID":73499,"market_name":"TODO元氣早午餐","addr":"宜蘭縣羅東鎮南門路48號","business_week":"星期一,星期二,星期三,星期四,星期五,星期六","context":"本店販售漢堡等早餐，使用優質國產豬肉","ValidDate":1713110400000,"Lontitude":121.768694,"Latitude":24.67301,"case_code":"2021032400114","created_user":"godspeed","created_date":1619982334000,"last_edited_user":"Developer","last_edited_date":1619996033000,"type":"餐飲","badge_code":"D004552","business_hours":"04:30","business_hours_end":"13:30","AddrToLonLatProcTime":1620023923000,"AddrToLonLatProcLog":"處理成功:TGOS","URL1":"https://taiwanpork.coa.gov.tw/files/food_data/13866/A01.jpg","URL2":"","URL3":""},"geometry":{"x":121.7686940000001,"y":24.673010000000033}},{"attributes":{"OBJECTID":73500,"market_name":"阿琴焢肉飯","addr":"宜蘭縣羅東鎮南昌街33-8號","business_week":"星期一,星期二,星期三,星期四,星期五,星期日","context":"本店經營焢肉飯等小吃，使用優質國產豬肉","ValidDate":1713110400000,"Lontitude":121.773956,"Latitude":24.672213,"case_code":"2021032400115","created_user":"godspeed","created_date":1619982345000,"last_edited_user":"Developer","last_edited_date":1619996033000,"type":"餐飲","badge_code":"D004553","business_hours":"10:00","business_hours_end":"14:00","AddrToLonLatProcTime":1620023923000,"AddrToLonLatProcLog":"處理成功:Google","URL1":"https://taiwanpork.coa.gov.tw/files/food_data/13867/A01.jpg","URL2":"","URL3":""},"geometry":{"x":121.77395600000011,"y":24.672213000000056}},{"attributes":{"OBJECTID":73501,"market_name":"三角張自助餐","addr":"宜蘭縣羅東鎮安平路1號","business_week":"星期一,星期二,星期三,星期四,星期五,星期六","context":"本店販售飯、菜、魚、肉(便當)，使用優質國產豬肉","ValidDate":1713110400000,"Lontitude":121.773463,"Latitude":24.6778,"case_code":"2021032400122","created_user":"godspeed","created_date":1619982363000,"last_edited_user":"Developer","last_edited_date":1619996033000,"type":"餐飲","badge_code":"D004555","business_hours":"07:00","business_hours_end":"15:00","AddrToLonLatProcTime":1620023923000,"AddrToLonLatProcLog":"處理成功:TGOS","URL1":"https://taiwanpork.coa.gov.tw/files/food_data/13874/A01.jpg","URL2":"","URL3":""},"geometry":{"x":121.77346300000011,"y":24.677800000000047}},{"attributes":{"OBJECTID":73502,"market_name":"金樽餐廳","addr":"宜蘭縣羅東鎮光榮路278號","business_week":"星期一,星期二,星期三,星期四,星期五,星期六,星期日","context":"大型婚宴會議、台菜海鮮餐廳","ValidDate":1713110400000,"Lontitude":121.770691,"Latitude":24.685994,"case_code":"2021032400125","created_user":"godspeed","created_date":1619982365000,"last_edited_user":"Developer","last_edited_date":1619996033000,"type":"餐飲","badge_code":"D004556","business_hours":"11:00","business_hours_end":"22:00","AddrToLonLatProcTime":1620023923000,"AddrToLonLatProcLog":"處理成功:TGOS","URL1":"https://taiwanpork.coa.gov.tw/files/food_data/13877/A01.jpg","URL2":"","URL3":""},"geometry":{"x":121.77069100000006,"y":24.685994000000051}},{"attributes":{"OBJECTID":73503,"market_name":" 品鮮海鮮餐廳","addr":"宜蘭縣五結鄉中興村大興路31號1樓","business_week":"星期一,星期二,星期三,星期四,星期五,星期六,星期日","context":"本店經營餐廳,專賣國產羊肉及國產豬肉\u003cbr /\u003e\r\n\u003cbr /\u003e\r\n","ValidDate":1713110400000,"Lontitude":121.780252,"Latitude":24.688013,"case_code":"2021032500002","created_user":"godspeed","created_date":1619982368000,"last_edited_user":"Developer","last_edited_date":1619996033000,"type":"餐飲","badge_code":"D004557","business_hours":"11:00","business_hours_end":"21:00","AddrToLonLatProcTime":1620023923000,"AddrToLonLatProcLog":"處理成功:TGOS","URL1":"https://taiwanpork.coa.gov.tw/files/food_data/13883/A01.jpg","URL2":"","URL3":""},"geometry":{"x":121.78025200000002,"y":24.688013000000069}},{"attributes":{"OBJECTID":73504,"market_name":"饡之香原創海鮮","addr":"宜蘭縣壯圍鄉美城村美功路二段158號","business_week":"星期二,星期三,星期四,星期五,星期六,星期日","context":"海鮮料理,使用國產優質豬肉\u003cbr /\u003e\r\n","ValidDate":1713110400000,"Lontitude":121.783762,"Latitude":24.783695,"case_code":"2021032500003","created_user":"godspeed","created_date":1619982370000,"last_edited_user":"Developer","last_edited_date":1619996033000,"type":"餐飲","badge_code":"D004558","business_hours":"10:00","business_hours_end":"21:00","AddrToLonLatProcTime":1620023923000,"AddrToLonLatProcLog":"處理成功:TGOS","URL1":"https://taiwanpork.coa.gov.tw/files/food_data/13884/A01.jpg","URL2":"","URL3":""},"geometry":{"x":121.78376200000002,"y":24.783695000000023}},{"attributes":{"OBJECTID":73505,"market_name":"貴蘭蔬菜號","addr":"宜蘭縣羅東鎮集祥里民生路6號","business_week":"星期一,星期二,星期三,星期四,星期五,星期六,星期日","context":"蔬  菜  行","ValidDate":1713110400000,"Lontitude":121.770921,"Latitude":24.676705,"case_code":"2021032500008","created_user":"godspeed","created_date":1619982373000,"last_edited_user":"Developer","last_edited_date":1619996033000,"type":"販售","badge_code":"D004559","business_hours":"08:00","business_hours_end":"17:00","AddrToLonLatProcTime":1620023923000,"AddrToLonLatProcLog":"處理成功:TGOS","URL1":"https://taiwanpork.coa.gov.tw/files/food_data/13889/A01.jpg","URL2":"","URL3":""},"geometry":{"x":121.77092100000004,"y":24.676705000000027}},{"attributes":{"OBJECTID":73506,"market_name":" 曹記牛肉麵","addr":"宜蘭縣羅東鎮成功里維揚路８號一樓","business_week":"星期一,星期二,星期三,星期四,星期五,星期六,星期日","context":"本店提供各類麵食與黑白切，豬肉製品皆採用優質國產豬肉","ValidDate":1713110400000,"Lontitude":121.762441,"Latitude":24.672751,"case_code":"2021032500010","created_user":"godspeed","created_date":1619982437000,"last_edited_user":"Developer","last_edited_date":1619996033000,"type":"販售","badge_code":"D004560","business_hours":"10:00","business_hours_end":"22:00","AddrToLonLatProcTime":1620023923000,"AddrToLonLatProcLog":"處理成功:TGOS","URL1":"https://taiwanpork.coa.gov.tw/files/food_data/13891/A01.jpg","URL2":"","URL3":""},"geometry":{"x":121.76244100000008,"y":24.672751000000062}},{"attributes":{"OBJECTID":73507,"market_name":"得味香自助餐","addr":"宜蘭縣羅東鎮光華街17號","business_week":"星期一,星期二,星期三,星期四,星期五,星期六","context":"本店為自助餐店","ValidDate":1713110400000,"Lontitude":121.759131,"Latitude":24.677609,"case_code":"2021032500013","created_user":"godspeed","created_date":1619982444000,"last_edited_user":"Developer","last_edited_date":1619996033000,"type":"餐飲","badge_code":"D004561","business_hours":"08:00","business_hours_end":"17:00","AddrToLonLatProcTime":1620023923000,"AddrToLonLatProcLog":"處理成功:TGOS","URL1":"https://taiwanpork.coa.gov.tw/files/food_data/13894/A01.jpg","URL2":"","URL3":""},"geometry":{"x":121.75913100000002,"y":24.677609000000075}},{"attributes":{"OBJECTID":73508,"market_name":"三媽臭臭鍋(羅東中山店)","addr":"宜蘭縣羅東鎮中山路二段305號","business_week":"星期一,星期二,星期三,星期四,星期五,星期六,星期日","context":"本店販售小火鍋，使用優質國產豬肉","ValidDate":1713110400000,"Lontitude":121.778592,"Latitude":24.674251,"case_code":"2021032500014","created_user":"godspeed","created_date":1619982446000,"last_edited_user":"Developer","last_edited_date":1619996033000,"type":"餐飲","badge_code":"D004562","business_hours":"11:00","business_hours_end":"22:00","AddrToLonLatProcTime":1620023923000,"AddrToLonLatProcLog":"處理成功:TGOS","URL1":"https://taiwanpork.coa.gov.tw/files/food_data/13895/A01.jpg","URL2":"","URL3":""},"geometry":{"x":121.77859200000012,"y":24.674251000000027}},{"attributes":{"OBJECTID":73509,"market_name":"大湖肉(米庚)","addr":"宜蘭縣員山鄉大湖路22之19號","business_week":"星期一,星期二,星期三,星期四,星期五,星期六,星期日","context":"麵、肉(米庚)、肉捲","ValidDate":1713110400000,"Lontitude":121.69947,"Latitude":24.745187,"case_code":"2021032500017","created_user":"godspeed","created_date":1619982447000,"last_edited_user":"Developer","last_edited_date":1619996033000,"type":"餐飲","badge_code":"D004563","business_hours":"06:00","business_hours_end":"14:00","AddrToLonLatProcTime":1620023923000,"AddrToLonLatProcLog":"處理成功:TGOS","URL1":"https://taiwanpork.coa.gov.tw/files/food_data/13898/A01.jpg","URL2":"","URL3":""},"geometry":{"x":121.69947000000002,"y":24.745187000000044}},{"attributes":{"OBJECTID":73510,"market_name":"炳宏快餐","addr":"宜蘭縣羅東鎮公正路241號","business_week":"星期一,星期二,星期三,星期四,星期五,星期六,星期日","context":"本店為便當店","ValidDate":1713110400000,"Lontitude":121.765389,"Latitude":24.679632,"case_code":"2021032500019","created_user":"godspeed","created_date":1619982448000,"last_edited_user":"Developer","last_edited_date":1619996033000,"type":"餐飲","badge_code":"D004564","business_hours":"08:00","business_hours_end":"17:00","AddrToLonLatProcTime":1620023923000,"AddrToLonLatProcLog":"處理成功:TGOS","URL1":"https://taiwanpork.coa.gov.tw/files/food_data/13900/A01.jpg","URL2":"","URL3":""},"geometry":{"x":121.76538900000003,"y":24.679632000000026}},{"attributes":{"OBJECTID":73511,"market_name":"牛鬥鱒魚大餐","addr":"宜蘭縣三星鄉泰雅一路462巷牛頭35號","business_week":"星期一,星期二,星期三,星期四,星期五,星期六,星期日","context":"本店為餐館、餐廳","ValidDate":1713110400000,"Lontitude":121.57658,"Latitude":24.640868,"case_code":"2021032500021","created_user":"godspeed","created_date":1619982454000,"last_edited_user":"Developer","last_edited_date":1619996033000,"type":"餐飲","badge_code":"D004565","business_hours":"11:00","business_hours_end":"18:00","AddrToLonLatProcTime":1620023923000,"AddrToLonLatProcLog":"處理成功:TGOS","URL1":"https://taiwanpork.coa.gov.tw/files/food_data/13902/A01.jpg","URL2":"","URL3":""},"geometry":{"x":121.57658000000004,"y":24.640868000000069}},{"attributes":{"OBJECTID":73512,"market_name":"一品珍肉鬆食品","addr":"宜蘭縣羅東鎮南門路114號","business_week":"星期二,星期三,星期四,星期五,星期六,星期日","context":"鎮內知名肉鬆店，自製自營肉鬆、肉乾等，均使用優質國產豬肉","ValidDate":1713110400000,"Lontitude":121.766428,"Latitude":24.673068,"case_code":"2021032500022","created_user":"godspeed","created_date":1619982456000,"last_edited_user":"Developer","last_edited_date":1619996033000,"type":"販售","badge_code":"D004566","business_hours":"09:00","business_hours_end":"20:00","AddrToLonLatProcTime":1620023923000,"AddrToLonLatProcLog":"處理成功:TGOS","URL1":"https://taiwanpork.coa.gov.tw/files/food_data/13903/A01.jpg","URL2":"","URL3":""},"geometry":{"x":121.76642800000002,"y":24.673068000000058}},{"attributes":{"OBJECTID":73513,"market_name":"劉家中式早點宵夜","addr":"宜蘭縣羅東鎮忠孝路5號","business_week":"星期一,星期二,星期三,星期四,星期五,星期六,星期日","context":"本店販售中式早點、湯包、蛋餅等產品","ValidDate":1713110400000,"Lontitude":121.764269,"Latitude":24.674602,"case_code":"2021032500031","created_user":"godspeed","created_date":1619982458000,"last_edited_user":"Developer","last_edited_date":1619996033000,"type":"餐飲","badge_code":"D004568","business_hours":"15:00","business_hours_end":"00:00","AddrToLonLatProcTime":1620023923000,"AddrToLonLatProcLog":"處理成功:TGOS","URL1":"https://taiwanpork.coa.gov.tw/files/food_data/13912/A01.jpg","URL2":"","URL3":""},"geometry":{"x":121.76426900000001,"y":24.67460200000005}},{"attributes":{"OBJECTID":73514,"market_name":" 程記炒飯","addr":"宜蘭縣羅東鎮民生路91號","business_week":"星期一,星期二,星期三,星期四,星期五,星期六,星期日","context":"本店販售炒飯、麵、燴飯等產品","ValidDate":1713110400000,"Lontitude":121.766451,"Latitude":24.677696,"case_code":"2021032500027","created_user":"godspeed","created_date":1619982460000,"last_edited_user":"Developer","last_edited_date":1619996033000,"type":"販售","badge_code":"D004567","business_hours":"11:00","business_hours_end":"20:00","AddrToLonLatProcTime":1620023923000,"AddrToLonLatProcLog":"處理成功:TGOS","URL1":"https://taiwanpork.coa.gov.tw/files/food_data/13908/A01.jpg","URL2":"","URL3":""},"geometry":{"x":121.76645100000007,"y":24.677696000000026}},{"attributes":{"OBJECTID":73515,"market_name":"品福饅頭.包子","addr":"宜蘭縣羅東鎮四育路142號","business_week":"星期一,星期二,星期三,星期四,星期五,星期六,星期日","context":"饅頭包子自製販售","ValidDate":1713110400000,"Lontitude":121.760865,"Latitude":24.679684,"case_code":"2021032500036","created_user":"godspeed","created_date":1619982466000,"last_edited_user":"Developer","last_edited_date":1619996033000,"type":"販售","badge_code":"D004569","business_hours":"06:30","business_hours_end":"15:00","AddrToLonLatProcTime":1620023923000,"AddrToLonLatProcLog":"處理成功:TGOS","URL1":"https://taiwanpork.coa.gov.tw/files/food_data/13917/A01.jpg","URL2":"","URL3":""},"geometry":{"x":121.76086500000008,"y":24.679684000000066}},{"attributes":{"OBJECTID":73516,"market_name":"成記牛肉麵","addr":"宜蘭縣冬山鄉群英路132號","business_week":"星期一,星期二,星期三,星期四,星期五,星期六","context":"本店販售牛肉麵、豬肉燴飯、滷肉飯等產品","ValidDate":1713110400000,"Lontitude":121.768127,"Latitude":24.668576,"case_code":"2021032500041","created_user":"godspeed","created_date":1619982482000,"last_edited_user":"Developer","last_edited_date":1619996033000,"type":"餐飲","badge_code":"D004570","business_hours":"11:00","business_hours_end":"19:30","AddrToLonLatProcTime":1620023923000,"AddrToLonLatProcLog":"處理成功:TGOS","URL1":"https://taiwanpork.coa.gov.tw/files/food_data/13922/A01.jpg","URL2":"","URL3":""},"geometry":{"x":121.76812700000005,"y":24.66857600000003}},{"attributes":{"OBJECTID":73517,"market_name":"厚臉皮水煎包","addr":"宜蘭縣羅東鎮四育路147號","business_week":"星期一,星期二,星期三,星期四,星期五,星期六,星期日","context":"自製豬肉水煎包、高麗菜水煎包等販售","ValidDate":1713110400000,"Lontitude":121.760765,"Latitude":24.680014,"case_code":"2021032500044","created_user":"godspeed","created_date":1619982484000,"last_edited_user":"Developer","last_edited_date":1619996033000,"type":"販售","badge_code":"D004571","business_hours":"06:00","business_hours_end":"18:00","AddrToLonLatProcTime":1620023923000,"AddrToLonLatProcLog":"處理成功:TGOS","URL1":"https://taiwanpork.coa.gov.tw/files/food_data/13925/A01.jpg","URL2":"","URL3":""},"geometry":{"x":121.76076500000011,"y":24.680014000000028}},{"attributes":{"OBJECTID":73518,"market_name":"中山鵝肉擔","addr":"宜蘭縣羅東鎮中山路二段419號","business_week":"星期一,星期二,星期三,星期四,星期五,星期六,星期日","context":"店內提供各類飯、麵、湯、小菜(各類肉品、海鮮、青菜)","ValidDate":1713110400000,"Lontitude":121.775696,"Latitude":24.675174,"case_code":"2021032500045","created_user":"godspeed","created_date":1619982502000,"last_edited_user":"Developer","last_edited_date":1619996033000,"type":"餐飲","badge_code":"D004572","business_hours":"10:30","business_hours_end":"22:00","AddrToLonLatProcTime":1620023923000,"AddrToLonLatProcLog":"處理成功:TGOS","URL1":"https://taiwanpork.coa.gov.tw/files/food_data/13926/A01.jpg","URL2":"","URL3":""},"geometry":{"x":121.77569600000004,"y":24.675174000000027}},{"attributes":{"OBJECTID":73519,"market_name":" 大方食坊","addr":"宜蘭縣羅東鎮四育路87號","business_week":"星期一,星期二,星期三,星期四,星期五,星期六","context":"販售各種飯食、小菜,招牌為滷肉飯、瓜仔肉飯","ValidDate":1713110400000,"Lontitude":121.760247,"Latitude":24.678362,"case_code":"2021032500046","created_user":"godspeed","created_date":1619982503000,"last_edited_user":"Developer","last_edited_date":1619996033000,"type":"餐飲","badge_code":"D004573","business_hours":"11:30","business_hours_end":"19:30","AddrToLonLatProcTime":1620023923000,"AddrToLonLatProcLog":"處理成功:TGOS","URL1":"https://taiwanpork.coa.gov.tw/files/food_data/13927/A01.jpg","URL2":"","URL3":""},"geometry":{"x":121.76024700000005,"y":24.67836200000005}},{"attributes":{"OBJECTID":73520,"market_name":"賣燥","addr":"宜蘭縣羅東鎮公正路248號","business_week":"星期一,星期二,星期三,星期四,星期五,星期六","context":"本店販售豬腳飯包、豬腳麵線等產品，使用優質國產豬肉","ValidDate":1713110400000,"Lontitude":121.766533,"Latitude":24.679611,"case_code":"2021032500049","created_user":"godspeed","created_date":1619982505000,"last_edited_user":"Developer","last_edited_date":1619996033000,"type":"餐飲","badge_code":"D004574","business_hours":"10:30","business_hours_end":"20:00","AddrToLonLatProcTime":1620023923000,"AddrToLonLatProcLog":"處理成功:TGOS","URL1":"https://taiwanpork.coa.gov.tw/files/food_data/13930/A01.jpg","URL2":"","URL3":""},"geometry":{"x":121.76653300000009,"y":24.679611000000023}},{"attributes":{"OBJECTID":73521,"market_name":"胖嘟嘟燒肉飯","addr":"宜蘭縣羅東鎮培英路92號","business_week":"星期一,星期二,星期三,星期四,星期五,星期六","context":"販賣燒肉飯、便當等","ValidDate":1713110400000,"Lontitude":121.759761,"Latitude":24.678263,"case_code":"2021032500051","created_user":"godspeed","created_date":1619982507000,"last_edited_user":"Developer","last_edited_date":1619996033000,"type":"餐飲","badge_code":"D004575","business_hours":"11:30","business_hours_end":"22:30","AddrToLonLatProcTime":1620023923000,"AddrToLonLatProcLog":"處理成功:TGOS","URL1":"https://taiwanpork.coa.gov.tw/files/food_data/13932/A01.jpg","URL2":"","URL3":""},"geometry":{"x":121.75976100000003,"y":24.678263000000072}},{"attributes":{"OBJECTID":73522,"market_name":" 正賀海鮮餐廳","addr":"宜蘭縣冬山鄉清溝路389號","business_week":"星期一,星期二,星期三,星期四,星期五,星期六,星期日","context":"經營台菜海鮮餐廳、外燴","ValidDate":1713110400000,"Lontitude":121.761032,"Latitude":24.656607,"case_code":"2021032500055","created_user":"godspeed","created_date":1619982508000,"last_edited_user":"Developer","last_edited_date":1619996033000,"type":"餐飲","badge_code":"D004576","business_hours":"11:00","business_hours_end":"20:00","AddrToLonLatProcTime":1620023923000,"AddrToLonLatProcLog":"處理成功:TGOS","URL1":"https://taiwanpork.coa.gov.tw/files/food_data/13936/A01.jpg","URL2":"","URL3":""},"geometry":{"x":121.76103200000011,"y":24.656607000000065}},{"attributes":{"OBJECTID":73523,"market_name":" 牛伯肉號","addr":"宜蘭縣羅東鎮中正路24巷10號(開元市場)","business_week":"星期三,星期四,星期五,星期六,星期日","context":"本店販售豬肉、香腸,使用優質國產豬","ValidDate":1713110400000,"Lontitude":121.770889,"Latitude":24.672965,"case_code":"2021032500058","created_user":"godspeed","created_date":1619982510000,"last_edited_user":"Developer","last_edited_date":1619996033000,"type":"販售","badge_code":"D004577","business_hours":"05:30","business_hours_end":"17:30","AddrToLonLatProcTime":1620023923000,"AddrToLonLatProcLog":"處理成功:TGOS","URL1":"https://taiwanpork.coa.gov.tw/files/food_data/13939/A01.jpg","URL2":"","URL3":""},"geometry":{"x":121.77088900000001,"y":24.672965000000033}},{"attributes":{"OBJECTID":73524,"market_name":"阿鳳","addr":"宜蘭縣三星鄉中興路二段345巷1號","business_week":"星期一,星期二,星期三,星期四,星期五,星期六,星期日","context":"本店販售麵、飯、黑白切等產品,使用優質國產豬肉","ValidDate":1713110400000,"Lontitude":121.687848,"Latitude":24.69398,"case_code":"2021032500061","created_user":"godspeed","created_date":1619982512000,"last_edited_user":"Developer","last_edited_date":1619996033000,"type":"餐飲","badge_code":"D004578","business_hours":"10:00","business_hours_end":"19:00","AddrToLonLatProcTime":1620023923000,"AddrToLonLatProcLog":"處理成功:TGOS","URL1":"https://taiwanpork.coa.gov.tw/files/food_data/13942/A01.jpg","URL2":"","URL3":""},"geometry":{"x":121.68784800000003,"y":24.693980000000067}},{"attributes":{"OBJECTID":73525,"market_name":"楊二姊自助餐","addr":"宜蘭縣五結鄉西河一路128巷27號","business_week":"星期一,星期二,星期三,星期四,星期五","context":"楊二姊自助餐,包飯、炒飯、炒麵","ValidDate":1713110400000,"Lontitude":121.764176,"Latitude":24.704663,"case_code":"2021032500065","created_user":"godspeed","created_date":1619982513000,"last_edited_user":"Developer","last_edited_date":1619996033000,"type":"餐飲","badge_code":"D004579","business_hours":"08:00","business_hours_end":"13:30","AddrToLonLatProcTime":1620023923000,"AddrToLonLatProcLog":"處理成功:TGOS","URL1":"https://taiwanpork.coa.gov.tw/files/food_data/13946/A01.jpg","URL2":"","URL3":""},"geometry":{"x":121.76417600000002,"y":24.704663000000039}},{"attributes":{"OBJECTID":73526,"market_name":"銀全成肉號","addr":"宜蘭縣羅東鎮民生路6號","business_week":"星期三,星期四,星期五,星期六,星期日","context":"本店販售豬肉,使用國產豬","ValidDate":1713110400000,"Lontitude":121.770921,"Latitude":24.676705,"case_code":"2021032500068","created_user":"godspeed","created_date":1619982534000,"last_edited_user":"Developer","last_edited_date":1619996033000,"type":"販售","badge_code":"D004580","business_hours":"05:00","business_hours_end":"15:00","AddrToLonLatProcTime":1620023923000,"AddrToLonLatProcLog":"處理成功:TGOS","URL1":"https://taiwanpork.coa.gov.tw/files/food_data/13949/A01.jpg","URL2":"","URL3":""},"geometry":{"x":121.77092100000004,"y":24.676705000000027}},{"attributes":{"OBJECTID":73527,"market_name":"可口點心","addr":"宜蘭縣羅東鎮大同路1-1號","business_week":"星期二,星期三,星期四,星期五,星期六,星期日","context":"肉粽、刈包,自製販售","ValidDate":1713110400000,"Lontitude":121.7722303,"Latitude":24.6781153,"case_code":"2021032500073","created_user":"godspeed","created_date":1619982539000,"last_edited_user":"Developer","last_edited_date":1619996033000,"type":"餐飲","badge_code":"D004581","business_hours":"10:00","business_hours_end":"00:00","AddrToLonLatProcTime":1620023923000,"AddrToLonLatProcLog":"處理成功:Google","URL1":"https://taiwanpork.coa.gov.tw/files/food_data/13954/A01.jpg","URL2":"","URL3":""},"geometry":{"x":121.77223030000005,"y":24.678115300000059}},{"attributes":{"OBJECTID":73528,"market_name":"合の味","addr":"宜蘭縣冬山鄉廣興路136號","business_week":"星期一,星期二,星期三,星期四,星期五,星期六","context":"本店販售飯、麵、湯粥等","ValidDate":1713110400000,"Lontitude":121.75046,"Latitude":24.670449,"case_code":"2021032500078","created_user":"godspeed","created_date":1619982541000,"last_edited_user":"Developer","last_edited_date":1619996033000,"type":"餐飲","badge_code":"D004582","business_hours":"11:00","business_hours_end":"21:00","AddrToLonLatProcTime":1620023923000,"AddrToLonLatProcLog":"處理成功:TGOS","URL1":"https://taiwanpork.coa.gov.tw/files/food_data/13959/A01.jpg","URL2":"","URL3":""},"geometry":{"x":121.75046000000009,"y":24.670449000000076}},{"attributes":{"OBJECTID":73529,"market_name":"中正堂焢肉飯","addr":"宜蘭縣羅東鎮中華路29-1號","business_week":"星期一,星期二,星期三,星期四,星期五,星期六","context":"本店販售焢肉飯等","ValidDate":1713110400000,"Lontitude":121.7663931,"Latitude":24.6767944,"case_code":"2021032500079","created_user":"godspeed","created_date":1619982543000,"last_edited_user":"Developer","last_edited_date":1619996033000,"type":"餐飲","badge_code":"D004583","business_hours":"05:30","business_hours_end":"22:00","AddrToLonLatProcTime":1620023923000,"AddrToLonLatProcLog":"處理成功:Google","URL1":"https://taiwanpork.coa.gov.tw/files/food_data/13960/A01.jpg","URL2":"","URL3":""},"geometry":{"x":121.76639310000007,"y":24.676794400000063}},{"attributes":{"OBJECTID":73530,"market_name":"羅東鎮農會購物中心","addr":"宜蘭縣羅東鎮倉前路14號","business_week":"星期一,星期二,星期三,星期四,星期五,星期六,星期日","context":"羅東鎮農會購物中心","ValidDate":1713110400000,"Lontitude":121.772533,"Latitude":24.680304,"case_code":"2021032500080","created_user":"godspeed","created_date":1619982547000,"last_edited_user":"Developer","last_edited_date":1619996033000,"type":"販售","badge_code":"D004584","business_hours":"08:30","business_hours_end":"17:00","AddrToLonLatProcTime":1620023923000,"AddrToLonLatProcLog":"處理成功:TGOS","URL1":"https://taiwanpork.coa.gov.tw/files/food_data/13961/A01.jpg","URL2":"","URL3":""},"geometry":{"x":121.77253300000007,"y":24.680304000000035}},{"attributes":{"OBJECTID":73531,"market_name":"南賓小吃部","addr":"宜蘭縣羅東鎮中正南路208號","business_week":"星期一,星期二,星期三,星期四,星期五,星期六","context":"本店販售麵食、滷肉飯、小菜等","ValidDate":1713110400000,"Lontitude":121.770401,"Latitude":24.672152,"case_code":"2021032500082","created_user":"godspeed","created_date":1619982552000,"last_edited_user":"Developer","last_edited_date":1619996033000,"type":"餐飲","badge_code":"D004586","business_hours":"09:00","business_hours_end":"20:00","AddrToLonLatProcTime":1620023923000,"AddrToLonLatProcLog":"處理成功:TGOS","URL1":"https://taiwanpork.coa.gov.tw/files/food_data/13963/A01.jpg","URL2":"","URL3":""},"geometry":{"x":121.77040100000011,"y":24.67215200000004}},{"attributes":{"OBJECTID":73532,"market_name":"駿懷舊餐廳","addr":"宜蘭縣羅東鎮純精路一段53號","business_week":"星期一,星期二,星期三,星期四,星期五,星期六,星期日","context":"","ValidDate":1713110400000,"Lontitude":121.765195,"Latitude":24.669433,"case_code":"2021032500084","created_user":"godspeed","created_date":1619982554000,"last_edited_user":"Developer","last_edited_date":1619996033000,"type":"餐飲","badge_code":"D004587","business_hours":"11:00","business_hours_end":"21:00","AddrToLonLatProcTime":1620023923000,"AddrToLonLatProcLog":"處理成功:TGOS","URL1":"https://taiwanpork.coa.gov.tw/files/food_data/13965/A01.jpg","URL2":"","URL3":""},"geometry":{"x":121.76519500000006,"y":24.669433000000026}},{"attributes":{"OBJECTID":73533,"market_name":"鼎灃","addr":"宜蘭縣蘇澳鎮龍德里龍祥二路6巷62號","business_week":"星期一,星期二,星期三,星期四,星期五","context":"販售外燴包飯中心","ValidDate":1713110400000,"Lontitude":121.826499,"Latitude":24.634848,"case_code":"2021032500091","created_user":"godspeed","created_date":1619982561000,"last_edited_user":"Developer","last_edited_date":1619996033000,"type":"工廠與製造","badge_code":"D004588","business_hours":"07:00","business_hours_end":"16:00","AddrToLonLatProcTime":1620023923000,"AddrToLonLatProcLog":"處理成功:TGOS","URL1":"https://taiwanpork.coa.gov.tw/files/food_data/13972/A01.jpg","URL2":"","URL3":""},"geometry":{"x":121.82649900000001,"y":24.634848000000034}},{"attributes":{"OBJECTID":73534,"market_name":"陳記肉焿","addr":"宜蘭縣羅東鎮集祥里長春路18號","business_week":"星期一,星期二,星期三,星期四,星期五,星期六,星期日","context":"本店販售肉羹、小菜等產品","ValidDate":1713110400000,"Lontitude":121.770456,"Latitude":24.677088,"case_code":"2021032500093","created_user":"godspeed","created_date":1619982564000,"last_edited_user":"Developer","last_edited_date":1619996033000,"type":"餐飲","badge_code":"D004589","business_hours":"08:00","business_hours_end":"20:00","AddrToLonLatProcTime":1620023923000,"AddrToLonLatProcLog":"處理成功:TGOS","URL1":"https://taiwanpork.coa.gov.tw/files/food_data/13974/A01.jpg","URL2":"","URL3":""},"geometry":{"x":121.77045600000008,"y":24.677088000000026}},{"attributes":{"OBJECTID":73535,"market_name":"珍味珍肉鬆","addr":"宜蘭縣羅東鎮中正南路一五七號","business_week":"星期一,星期二,星期三,星期四,星期五,星期六","context":"純手工精製肉品專賣店","ValidDate":1713110400000,"Lontitude":121.770518,"Latitude":24.671468,"case_code":"2021032500095","created_user":"godspeed","created_date":1619982582000,"last_edited_user":"Developer","last_edited_date":1619996033000,"type":"販售","badge_code":"D004590","business_hours":"08:00","business_hours_end":"20:00","AddrToLonLatProcTime":1620023923000,"AddrToLonLatProcLog":"處理成功:TGOS","URL1":"https://taiwanpork.coa.gov.tw/files/food_data/13976/A01.jpg","URL2":"","URL3":""},"geometry":{"x":121.77051800000004,"y":24.671468000000061}},{"attributes":{"OBJECTID":73536,"market_name":"岑家牛豬肉麵","addr":"宜蘭縣羅東鎮成功里興東南路237號1樓","business_week":"星期一,星期二,星期三,星期四,星期五,星期六","context":"本店販售紅燒豬肉麵、牛肉麵等","ValidDate":1713110400000,"Lontitude":121.767182,"Latitude":24.672431,"case_code":"2021032500097","created_user":"godspeed","created_date":1619982587000,"last_edited_user":"Developer","last_edited_date":1619996033000,"type":"餐飲","badge_code":"D004591","business_hours":"11:00","business_hours_end":"20:00","AddrToLonLatProcTime":1620023923000,"AddrToLonLatProcLog":"處理成功:TGOS","URL1":"https://taiwanpork.coa.gov.tw/files/food_data/13978/A01.jpg","URL2":"","URL3":""},"geometry":{"x":121.76718200000005,"y":24.672431000000074}},{"attributes":{"OBJECTID":73537,"market_name":"李老師牛肉麵","addr":"宜蘭縣羅東鎮公正里公正路268號1樓","business_week":"星期一,星期二,星期三,星期四,星期五,星期六","context":"本店專賣豬腳、肉燥飯(麵)","ValidDate":1713110400000,"Lontitude":121.765703,"Latitude":24.679814,"case_code":"2021032500099","created_user":"godspeed","created_date":1619982589000,"last_edited_user":"Developer","last_edited_date":1619996033000,"type":"餐飲","badge_code":"D004592","business_hours":"11:00","business_hours_end":"20:00","AddrToLonLatProcTime":1620023923000,"AddrToLonLatProcLog":"處理成功:TGOS","URL1":"https://taiwanpork.coa.gov.tw/files/food_data/13980/A01.jpg","URL2":"","URL3":""},"geometry":{"x":121.76570300000003,"y":24.679814000000079}},{"attributes":{"OBJECTID":73538,"market_name":"辣媽麵食坊","addr":"宜蘭縣羅東鎮大新里大同路3號","business_week":"星期一,星期二,星期三,星期四,星期五,星期六","context":"本店販售肉燥、餛飩、嘴邊肉","ValidDate":1713110400000,"Lontitude":121.772253,"Latitude":24.678227,"case_code":"2021032500101","created_user":"godspeed","created_date":1619982590000,"last_edited_user":"Developer","last_edited_date":1619996033000,"type":"餐飲","badge_code":"D004593","business_hours":"07:00","business_hours_end":"19:00","AddrToLonLatProcTime":1620023923000,"AddrToLonLatProcLog":"處理成功:TGOS","URL1":"https://taiwanpork.coa.gov.tw/files/food_data/13982/A01.jpg","URL2":"","URL3":""},"geometry":{"x":121.77225300000009,"y":24.678227000000049}},{"attributes":{"OBJECTID":73539,"market_name":"金鼎園日式涮涮鍋","addr":"宜蘭縣羅東鎮北成里北成路2段206巷7號一樓","business_week":"星期一,星期二,星期三,星期四,星期五,星期六,星期日","context":"本店專賣火鍋","ValidDate":1713110400000,"Lontitude":121.749896,"Latitude":24.681861,"case_code":"2021032500104","created_user":"godspeed","created_date":1619982593000,"last_edited_user":"Developer","last_edited_date":1619996033000,"type":"餐飲","badge_code":"D004594","business_hours":"11:00","business_hours_end":"22:00","AddrToLonLatProcTime":1620023923000,"AddrToLonLatProcLog":"處理成功:TGOS","URL1":"https://taiwanpork.coa.gov.tw/files/food_data/13985/A01.jpg","URL2":"","URL3":""},"geometry":{"x":121.74989600000004,"y":24.681861000000026}},{"attributes":{"OBJECTID":73540,"market_name":"藏之田料理屋","addr":"宜蘭縣羅東鎮民生東路32號","business_week":"星期二,星期三,星期四,星期五,星期六,星期日","context":"本店為經營日本料理餐廳，使用優質國產豬肉","ValidDate":1713110400000,"Lontitude":121.773308,"Latitude":24.675868,"case_code":"2021032400119","created_user":"godspeed","created_date":1619984033000,"last_edited_user":"Developer","last_edited_date":1619996033000,"type":"餐飲","badge_code":"D004554","business_hours":"11:00","business_hours_end":"21:00","AddrToLonLatProcTime":1620023923000,"AddrToLonLatProcLog":"處理成功:TGOS","URL1":"https://taiwanpork.coa.gov.tw/files/food_data/13871/A01.jpg","URL2":"","URL3":""},"geometry":{"x":121.77330800000004,"y":24.675868000000037}},{"attributes":{"OBJECTID":73710,"market_name":"宏大便當店","addr":"臺中市大雅區永和路11-33號","business_week":"星期一,星期二,星期三,星期四,星期五,星期六","context":"本店使用國產豬肉","ValidDate":1713801600000,"Lontitude":120.6294175,"Latitude":24.2076837,"case_code":"2021040100018","created_user":"godspeed","created_date":1619670612000,"last_edited_user":"Developer","last_edited_date":1619996033000,"type":"餐飲","badge_code":"D004953","business_hours":"10:00","business_hours_end":"14:00","AddrToLonLatProcTime":1620023923000,"AddrToLonLatProcLog":"處理成功:Google","URL1":"https://taiwanpork.coa.gov.tw/files/food_data/14421/A01.jpg","URL2":"","URL3":""},"geometry":{"x":120.62941750000005,"y":24.207683700000075}},{"attributes":{"OBJECTID":73711,"market_name":" 熊也炭烤","addr":"臺中市豐原區中興路25號","business_week":"星期一,星期二,星期三,星期四,星期五,星期六","context":"炒飯  炒麵   快炒","ValidDate":1713801600000,"Lontitude":120.718346,"Latitude":24.248159,"case_code":"2021040600058","created_user":"godspeed","created_date":1619670620000,"last_edited_user":"Developer","last_edited_date":1619996033000,"type":"餐飲","badge_code":"D004959","business_hours":"10:00","business_hours_end":"20:00","AddrToLonLatProcTime":1620023923000,"AddrToLonLatProcLog":"處理成功:TGOS","URL1":"https://taiwanpork.coa.gov.tw/files/food_data/14551/A01.jpg","URL2":"","URL3":""},"geometry":{"x":120.71834600000011,"y":24.248159000000044}}]}